README.md
cozir.py
setup.py
micropython_cozir.egg-info/PKG-INFO
micropython_cozir.egg-info/SOURCES.txt
micropython_cozir.egg-info/dependency_links.txt
micropython_cozir.egg-info/top_level.txt