Metadata-Version: 2.1
Name: micropython-cozir
Version: 0.1.5
Summary: COZIR CO2 Sensor Library
Home-page: https://github.com/dml/micropython-cozir
Author: Dmitry Larkin
Author-email: dmitry.larkin@gmail.com
Maintainer: Dmitry Larkin
Maintainer-email: dmitry.larkin@gmail.com
License: MIT
Keywords: COZIR CO2 Sensor micropython
Platform: UNKNOWN
Classifier: Development Status :: 4 - Beta
Classifier: Programming Language :: Python :: Implementation :: MicroPython
Classifier: License :: OSI Approved :: MIT License
